thanhtungthaiatmethod/__init__.py
thanhtungthaiatmethod/fortest.py
thanhtungthaiatmethod/methodprimary.py
thanhtungthaiatmethod/methods.py
thanhtungthaiatmethod-3.1.0.dist-info/LICENSE
thanhtungthaiatmethod-3.1.0.dist-info/METADATA
thanhtungthaiatmethod-3.1.0.dist-info/WHEEL
thanhtungthaiatmethod-3.1.0.dist-info/top_level.txt
thanhtungthaiatmethod-3.1.0.dist-info/RECORD
