Metadata-Version: 2.1
Name: thanhtungthaiatmethod
Version: 3.1.0
Summary: All method for calculate Thai at
Home-page: https://github.com/pypa/sampleproject
Author: Thanh Tung
Author-email: thanhtung247@gmail.com
Project-URL: Bug Tracker, https://github.com/pypa/sampleproject/issues
Classifier: Programming Language :: Python :: 3
Classifier: License :: OSI Approved :: MIT License
Classifier: Operating System :: OS Independent
Requires-Python: >=3.6
License-File: LICENSE
